cfig/__init__.py
cfig/config.py
cfig/customtyping.py
cfig/errors.py
cfig/sample/__init__.py
cfig/sample/definition.py
cfig/sample/usage.py
cfig/sources/base.py
cfig/sources/env.py
cfig/sources/envfile.py
cfig/tests/test_config.py
cfig-0.3.10.dist-info/METADATA
cfig-0.3.10.dist-info/WHEEL
cfig-0.3.10.dist-info/licenses/LICENSE.txt
cfig-0.3.10.dist-info/RECORD
