Metadata-Version: 2.4
Name: cfig
Version: 0.3.10
Summary: A configuration manager for Python
License-Expression: MIT
License-File: LICENSE.txt
Keywords: configuration,config,lazy,environment,envvars
Author: Stefano Pigozzi
Author-email: me@steffo.eu
Maintainer: Stefano Pigozzi
Maintainer-email: me@steffo.eu
Requires-Python: >=3.11,<4.0
Classifier: Programming Language :: Python :: 3
Classifier: Programming Language :: Python :: 3.11
Classifier: Development Status :: 3 - Alpha
Classifier: Environment :: Console
Classifier: Intended Audience :: Developers
Classifier: Intended Audience :: System Administrators
Classifier: License :: OSI Approved :: MIT License
Classifier: Operating System :: OS Independent
Classifier: Topic :: Software Development
Classifier: Topic :: System :: Software Distribution
Classifier: Typing :: Typed
Provides-Extra: cli
Requires-Dist: click (>=8.1.2,<9.0.0) ; extra == "cli"
Requires-Dist: colorama (>=0.4.4,<0.5.0) ; extra == "cli"
Requires-Dist: lazy-object-proxy (>=1.7.1,<2.0.0)
Project-URL: Documentation, https://artifacts.steffo.eu/steffo/cfig/
Project-URL: Issues, https://forge.steffo.eu/steffo/cfig/issues
Project-URL: Source, https://forge.steffo.eu/steffo/cfig
